clfd/__init__.py
clfd/_version.py
clfd/archive_handler.py
clfd/profile_masking.py
clfd/report.py
clfd/report_plotting.py
clfd/serialization.py
clfd/spike_finding.py
clfd/apps/__init__.py
clfd/apps/cleanup.py
clfd/apps/functions.py
clfd/features/__init__.py
clfd/features/functions.py
clfd/features/register.py
clfd-1.0.1.dist-info/LICENSE
clfd-1.0.1.dist-info/METADATA
clfd-1.0.1.dist-info/WHEEL
clfd-1.0.1.dist-info/entry_points.txt
clfd-1.0.1.dist-info/top_level.txt
clfd-1.0.1.dist-info/RECORD
