Metadata-Version: 2.1
Name: clfd
Version: 1.0.1
Summary: Smart RFI removal algorithms to be used on folded pulsar search and timing data
Author-email: Vincent Morello <vmorello@gmail.com>
License: MIT License
Project-URL: homepage, https://github.com/v-morello/clfd
Classifier: Programming Language :: Python :: 3.9
Classifier: Programming Language :: Python :: 3.10
Classifier: Programming Language :: Python :: 3.11
Classifier: Programming Language :: Python :: 3.12
Classifier: Programming Language :: Python :: 3.13
Classifier: License :: OSI Approved :: MIT License
Classifier: Operating System :: Unix
Classifier: Topic :: Scientific/Engineering :: Astronomy
Requires-Python: >=3.9
License-File: LICENSE
Requires-Dist: numpy<2.0.0
Requires-Dist: matplotlib
Provides-Extra: dev
Requires-Dist: isort; extra == "dev"
Requires-Dist: flake8; extra == "dev"
Requires-Dist: black; extra == "dev"
Requires-Dist: pytest; extra == "dev"
Requires-Dist: pytest-cov; extra == "dev"
Requires-Dist: build; extra == "dev"
Requires-Dist: twine; extra == "dev"
